wiktrola/__init__.py
wiktrola/script.py
wiktrola/wiki.j2
wiktrola/wiktrola.py
wiktrola-1.0.2.dist-info/entry_points.txt
wiktrola-1.0.2.dist-info/LICENSE
wiktrola-1.0.2.dist-info/WHEEL
wiktrola-1.0.2.dist-info/METADATA
wiktrola-1.0.2.dist-info/RECORD
