Metadata-Version: 2.1
Name: wiktrola
Version: 1.0.2
Summary: Transform any Wikipedia article into an MP3
Author: John Capobianco
Author-email: ptcapo@gmail.com
Requires-Python: >=3.8,<4.0
Classifier: Programming Language :: Python :: 3
Classifier: Programming Language :: Python :: 3.10
Classifier: Programming Language :: Python :: 3.8
Classifier: Programming Language :: Python :: 3.9
Requires-Dist: Jinja2 (>=3.1.2,<4.0.0)
Requires-Dist: gTTS (>=2.2.4,<3.0.0)
Requires-Dist: rich-click (>=1.3.0,<2.0.0)
Requires-Dist: wikipedia (>=1.4.0,<2.0.0)
